efficient_ocr/__init__.py
efficient_ocr/detection/__init__.py
efficient_ocr/detection/detector.py
efficient_ocr/detection/linemodel.py
efficient_ocr/detection/localizermodel.py
efficient_ocr/model/__init__.py
efficient_ocr/model/effocr.py
efficient_ocr/recognition/__init__.py
efficient_ocr/recognition/infer_recognize.py
efficient_ocr/recognition/recognizermodel.py
efficient_ocr/utils/__init__.py
efficient_ocr/utils/default_config.py
efficient_ocr/utils/gcv_bootstrap.py
efficient_ocr/utils/misc.py
efficient_ocr/utils/onnx.py
efficient_ocr/utils/ops.py
efficient_ocr/utils/text.py
efficient_ocr/utils/transforms.py
efficient_ocr/utils/yolo.py
efficient_ocr/utils/recognition/__init__.py
efficient_ocr/utils/recognition/custom_schedulers.py
efficient_ocr/utils/recognition/datasets.py
efficient_ocr/utils/recognition/encoders.py
efficient_ocr/utils/recognition/samplers.py
efficient_ocr/utils/recognition/synth_crops.py
efficient_ocr/utils/recognition/transforms.py
efficient_ocr-0.1.1.dist-info/LICENSE
efficient_ocr-0.1.1.dist-info/METADATA
efficient_ocr-0.1.1.dist-info/WHEEL
efficient_ocr-0.1.1.dist-info/top_level.txt
efficient_ocr-0.1.1.dist-info/RECORD
