Metadata-Version: 2.1
Name: efficient-ocr
Version: 0.1.1
Summary: Efficient OCR
Home-page: https://github.com/dell-research-harvard/efficient_ocr
Author: Tom Bryan, Abhishek Arora, Jacob Carlson, Ethan C. Tan
Author-email: bryanptom@gmail.com
License: Apache-2.0
Keywords: layout analysis,deep learning
Platform: UNKNOWN
Classifier: Intended Audience :: Developers
Classifier: Intended Audience :: Education
Classifier: Intended Audience :: Science/Research
Classifier: License :: OSI Approved :: Apache Software License
Classifier: Programming Language :: Python :: 3
Classifier: Programming Language :: Python :: 3.6
Classifier: Programming Language :: Python :: 3.7
Classifier: Programming Language :: Python :: 3.8
Classifier: Programming Language :: Python :: 3.9
Classifier: Topic :: Scientific/Engineering :: Artificial Intelligence
Requires-Python: >=3.6
License-File: LICENSE
Requires-Dist: numpy
Requires-Dist: opencv-python
Requires-Dist: scipy
Requires-Dist: pandas
Requires-Dist: pillow
Requires-Dist: pyyaml (>=5.1)
Requires-Dist: iopath
Requires-Dist: pdfplumber
Requires-Dist: pdf2image
Requires-Dist: onnxruntime
Requires-Dist: onnx
Requires-Dist: faiss-cpu
Requires-Dist: yolov5 (<=7.0.10)
Requires-Dist: timm
Requires-Dist: huggingface-hub (==0.24.7)
Requires-Dist: kornia
Requires-Dist: pytorch-metric-learning (==1.6.3)
Requires-Dist: transformers (==4.45.0)
Requires-Dist: albumentations
Requires-Dist: wandb
Requires-Dist: requests
